{
  "type": "lesson",
  "self": "problems/section4/lesson3.json",
  "code": "problems/section4/lesson3.code",
  "module": "section4",

  "lesson": "Lesson 3 - Assignments with a purpose",

  "previousLesson": "problems/section4/lesson2.json",
  "nextLessonOnSuccess": "problems/section4/lesson4.json",
  "nextLessonOnFailure": "problems/section4/lesson3.json",

  "referenceMaterial": "<p>At the place marked by <b>Remember</b>, values of variables such as I and J are assumed to be #I and #J.</p>"
}
